objbrowser/__init__.py
objbrowser/app.py
objbrowser/attribute_model.py
objbrowser/objectbrowser.py
objbrowser/toggle_column_mixin.py
objbrowser/treeitem.py
objbrowser/treemodel.py
objbrowser/utils.py
objbrowser/version.py
objbrowser-1.3.1.dist-info/LICENSE.txt
objbrowser-1.3.1.dist-info/METADATA
objbrowser-1.3.1.dist-info/WHEEL
objbrowser-1.3.1.dist-info/top_level.txt
objbrowser-1.3.1.dist-info/RECORD
