Metadata-Version: 2.1
Name: objbrowser
Version: 1.3.1
Summary: GUI for Python object introspection.
Home-page: https://github.com/titusjan/objbrowser
Author: Pepijn Kenter
Author-email: titusjan@gmail.com
License: UNKNOWN
Platform: UNKNOWN
Classifier: Development Status :: 5 - Production/Stable
Classifier: Environment :: X11 Applications :: Qt
Classifier: Intended Audience :: Developers
Classifier: License :: OSI Approved :: MIT License
Classifier: Natural Language :: English
Classifier: Operating System :: MacOS :: MacOS X
Classifier: Operating System :: Microsoft :: Windows
Classifier: Operating System :: POSIX :: Linux
Classifier: Programming Language :: Python
Classifier: Topic :: Adaptive Technologies
Classifier: Topic :: Software Development
Classifier: Topic :: Utilities
License-File: LICENSE.txt
Requires-Dist: six
Requires-Dist: qtpy
